dags/__init__.py
dags/configuration.json
dags/dag_fetcher.py
dags/tester.py
dags/events/__init__.py
dags/events/accepted_pipeline.py
dags/events/delete_pipeline.py
dags/events/failed_pipeline.py
dags/events/new_pipeline.py
dags/events/submitted_pipeline.py
dags/operators/__init__.py
dags/operators/dgp_kind/__init__.py
dags/operators/dgp_kind/fileloader.py
dags/operators/printer/__init__.py
etl_server/VERSION
etl_server/__init__.py
etl_server/db_utils.py
etl_server/permissions.py
etl_server/datarecords/__init__.py
etl_server/datarecords/blueprint.py
etl_server/datarecords/controllers.py
etl_server/datarecords/models.py
etl_server/files/__init__.py
etl_server/files/blueprint.py
etl_server/files/controllers.py
etl_server/loaders/__init__.py
etl_server/loaders/fileloader.py
etl_server/pipelines/__init__.py
etl_server/pipelines/blueprint.py
etl_server/pipelines/cache.py
etl_server/pipelines/controllers.py
etl_server/pipelines/models.py
etl_server/taxonomies/__init__.py
etl_server/taxonomies/blueprint.py
etl_server/taxonomies/controllers.py
etl_server/taxonomies/models.py
etl_server/users/__init__.py
etl_server/users/blueprint.py
etl_server/users/controllers.py
etl_server/users/models.py
etl_server-0.0.13.dist-info/LICENSE
etl_server-0.0.13.dist-info/METADATA
etl_server-0.0.13.dist-info/WHEEL
etl_server-0.0.13.dist-info/top_level.txt
etl_server-0.0.13.dist-info/RECORD
