Metadata-Version: 2.1
Name: etl-server
Version: 0.0.13
Summary: {{ DESCRIPTION }}
Home-page: https://github.com/akariv
Author: Adam Kariv
License: MIT
Keywords: data,ckan
Platform: UNKNOWN
Classifier: Development Status :: 4 - Beta
Classifier: Environment :: Web Environment
Classifier: Intended Audience :: Developers
Classifier: License :: OSI Approved :: MIT License
Classifier: Operating System :: OS Independent
Classifier: Programming Language :: Python :: 3.6
Classifier: Topic :: Internet :: WWW/HTTP :: Dynamic Content
Classifier: Topic :: Software Development :: Libraries :: Python Modules
Requires-Dist: aiopg
Requires-Dist: dgp-oauth2 (>=1.0.7)
Requires-Dist: sqlalchemy (==1.3.23)
Requires-Dist: flask-cors
Requires-Dist: flask-jsonpify
Requires-Dist: flask-session
Requires-Dist: PyYAML
Requires-Dist: python-slugify
Requires-Dist: psycopg2-binary
Requires-Dist: requests
Requires-Dist: dgp-server (>=0.0.91)
Requires-Dist: dgp (>=0.0.96)
Requires-Dist: geocoder
Requires-Dist: pyproj
Requires-Dist: dataflows (>=0.3.15)
Requires-Dist: tabulator[html] (>=1.48)
Requires-Dist: tableschema (>=1.18)
Requires-Dist: cattrs (<1.1.0)
Requires-Dist: wtforms (<3)
Requires-Dist: markupsafe (==2.0.1)
Provides-Extra: develop
Requires-Dist: pylama ; extra == 'develop'
Requires-Dist: tox ; extra == 'develop'
Requires-Dist: coverage ; extra == 'develop'
Requires-Dist: coveralls ; extra == 'develop'
Requires-Dist: pytest ; extra == 'develop'
Requires-Dist: pytest-cov ; extra == 'develop'
Requires-Dist: requests-mock (==1.3.0) ; extra == 'develop'
